vetiver/__init__.py
vetiver/attach_pkgs.py
vetiver/helpers.py
vetiver/meta.py
vetiver/mock.py
vetiver/monitor.py
vetiver/pin_read_write.py
vetiver/prototype.py
vetiver/rsconnect.py
vetiver/server.py
vetiver/templates.py
vetiver/types.py
vetiver/utils.py
vetiver/vetiver_model.py
vetiver/write_docker.py
vetiver/write_fastapi.py
vetiver/data/__init__.py
vetiver/data/chicago.csv
vetiver/data/mtcars.csv
vetiver/data/sacramento.csv
vetiver/handlers/__init__.py
vetiver/handlers/base.py
vetiver/handlers/sklearn.py
vetiver/handlers/spacy.py
vetiver/handlers/statsmodels.py
vetiver/handlers/torch.py
vetiver/handlers/xgboost.py
vetiver/templates/model_card.qmd
vetiver/templates/monitoring_dashboard.qmd
vetiver/tests/__init__.py
vetiver/tests/conftest.py
vetiver/tests/rsconnect_api_keys.json
vetiver/tests/test_add_endpoint.py
vetiver/tests/test_custom_handler.py
vetiver/tests/test_mock_data.py
vetiver/tests/test_monitor.py
vetiver/tests/test_pin_write.py
vetiver/tests/test_prepare_docker.py
vetiver/tests/test_pytorch.py
vetiver/tests/test_rsconnect.py
vetiver/tests/test_server.py
vetiver/tests/test_sklearn.py
vetiver/tests/test_spacy.py
vetiver/tests/test_statsmodels.py
vetiver/tests/test_templates.py
vetiver/tests/test_vetiver_model.py
vetiver/tests/test_write_app.py
vetiver/tests/test_write_docker.py
vetiver/tests/test_xgboost.py
vetiver/tests/snapshots/monitoring_dashboard.qmd
vetiver/tests/snapshots/test_monitor.json
vetiver-0.2.6.dist-info/LICENSE
vetiver-0.2.6.dist-info/METADATA
vetiver-0.2.6.dist-info/WHEEL
vetiver-0.2.6.dist-info/top_level.txt
vetiver-0.2.6.dist-info/RECORD
