Metadata-Version: 2.1
Name: vetiver
Version: 0.2.6
Summary: Version, share, deploy, and monitor models.
Author-email: Isabel Zimmerman <isabel.zimmerman@posit.co>
License: MIT
Project-URL: homepage, https://github.com/rstudio/vetiver-python
Project-URL: documentation, https://rstudio.github.io/vetiver-python/stable/
Keywords: data,mlops
Classifier: Programming Language :: Python :: 3.9
Classifier: Programming Language :: Python :: 3.10
Classifier: Programming Language :: Python :: 3.11
Classifier: Programming Language :: Python :: 3.12
Classifier: Programming Language :: Python :: 3.13
Requires-Python: >=3.9
License-File: LICENSE
Requires-Dist: numpy
Requires-Dist: pandas
Requires-Dist: fastapi
Requires-Dist: pydantic
Requires-Dist: joblib
Requires-Dist: uvicorn
Requires-Dist: scikit-learn
Requires-Dist: nest-asyncio
Requires-Dist: requests
Requires-Dist: pins>=0.7.1
Requires-Dist: rsconnect-python>=1.11.0
Requires-Dist: python-dotenv
Requires-Dist: plotly
Requires-Dist: pip-tools
Requires-Dist: httpx
Provides-Extra: all
Requires-Dist: vetiver[dev]; extra == "all"
Requires-Dist: vetiver[all_models]; extra == "all"
Requires-Dist: vetiver[docs]; extra == "all"
Provides-Extra: all-models
Requires-Dist: vetiver[torch]; extra == "all-models"
Requires-Dist: vetiver[statsmodels]; extra == "all-models"
Requires-Dist: vetiver[xgboost]; extra == "all-models"
Requires-Dist: vetiver[spacy]; extra == "all-models"
Provides-Extra: dev
Requires-Dist: pytest; extra == "dev"
Requires-Dist: pytest-cov; extra == "dev"
Requires-Dist: pytest-snapshot; extra == "dev"
Requires-Dist: vetiver[typecheck]; extra == "dev"
Requires-Dist: vetiver[docs]; extra == "dev"
Provides-Extra: docs
Requires-Dist: quartodoc; extra == "docs"
Requires-Dist: jupyter; extra == "docs"
Provides-Extra: statsmodels
Requires-Dist: statsmodels; extra == "statsmodels"
Provides-Extra: torch
Requires-Dist: torch; extra == "torch"
Provides-Extra: xgboost
Requires-Dist: xgboost; extra == "xgboost"
Provides-Extra: spacy
Requires-Dist: spacy; python_version < "3.13" and extra == "spacy"
Provides-Extra: typecheck
Requires-Dist: pyright; extra == "typecheck"
Requires-Dist: pandas-stubs; extra == "typecheck"
